[{"name":"Janeii","password":"12345678","level":"1","date":"26/11/2023","time_in":"","id":"303"},{"name":"Janeiii","password":"12345678","level":"2","date":"26/11/2023","time_in":"","id":"69"},{"name":"ryan","password":"12345678","level":"1","date":"26/11/2023","time_in":"","id":"1"},{"name":"edward","password":"12345678","level":"1","date":"26/11/2023","time_in":"","id":"2"},{"name":"john","password":"12345678","level":"1","date":"26/11/2023","time_in":"","id":"11"},{"name":"testone","password":"12345678","level":"1","date":"26/11/2023","time_in":"","id":"788"},{"name":"testtwo","password":"12345678","level":"1","date":"26/11/2023","time_in":"","id":"11"}]